{
    "items": [
    
        {
            "type": "plugin",
            "title": "[COLORyellow]JoBlo Movie Trailers Click Here!![/COLOR]",
            "link": "plugin://plugin.video.youtube/channel/UCT37npEfScFdfHeiIOpFKJg/",
            "thumbnail": "https://i.imgur.com/dn3xuf0.png"
        },
        {
            "type": "dir",
            "title": "[COLORlime]All Movies 1080p Where Possible[/COLOR]",
            "link": "https://"
        },
        {
            "type": "item",
            "title": "Cabin Tales (2023)",
            "link": [
            "https://dood.yt/d/no3rfmjb4k88"
        ],
            "thumbnail": "https://i.imgur.com/I4eAOmy.jpg",
            "imdb": "tt21110216"
        },
        {
            "type": "item",
            "title": "The Offering (2023)",
            "link": [
            "https://hexupload.net/tpmswinm7ey9([COLORlime]FHD[/COLOR])"
        ],
            "thumbnail": "https://i.imgur.com/0tyZSJL.jpg",
            "summary": "Horror",
            "imdb": "tt13103732"
        },
        {
            "type": "item",
            "title": "You People (2023)",
            "link": [
            "https://racaty.io/8rt8pocjhq7a([COLORlime]FHD[/COLOR])"
        ],
            "thumbnail": "https://i.imgur.com/4mscDFH.jpg",
            "imdb": "tt14826022"
        },
        {
            "type": "item",
            "title": "Summertime Dropouts (2022)",
            "link": [
            "https://racaty.io/49mhjv4bzxdy([COLORlime]FHD[/COLOR])"
        ],
            "thumbnail": "https://i.imgur.com/VZdDP8p.jpg",
            "imdb": "tt6666116"
        },
        {
            "type": "item",
            "title": "Stranger (2022)",
            "link": [
            "https://racaty.io/zo3jdx1eo3z4([COLORlime]FHD[/COLOR])"
        ],
            "thumbnail": "https://i.imgur.com/YZncADQ.jpg",
            "imdb": "tt21220892"
        },
        {
            "type": "item",
            "title": "Birdemic 3: Sea Eagle (2022)",
            "link": [
            "https://hexupload.net/nwe4qk3dqf89([COLORlime]FHD[/COLOR])"
        ],
            "thumbnail": "https://i.imgur.com/wFVSDFd.jpg",
            "imdb": "tt15701872"
        },
        {
            "type": "item",
            "title": "Shark Waters (2022)",
            "link": [
            "https://hexupload.net/kmsv3ekn0h1x([COLORlime]FHD[/COLOR])"
        ],
            "thumbnail": "https://i.imgur.com/VHJJlRM.jpg",
            "imdb": "tt21816892"
        },
        {
            "type": "item",
            "title": "Alone at Night (2023)",
            "link": [
            "https://hexupload.net/v2ecipajztf8([COLORlime]FHD[/COLOR])"
        ],
            "thumbnail": "https://i.imgur.com/U65Knc7.jpg",
            "imdb": "tt14409938"
        },
        {
            "type": "item",
            "title": "Shotgun Wedding (2022)",
            "link": [
            "https://hexupload.net/dtxtgmalysn5([COLORlime]FHD[/COLOR])"
        ],
            "thumbnail": "https://i.imgur.com/JITofuh.jpg",
            "summary": "Action/Comedy/Romance",
            "imdb": "tt9686790"
        },
        {
            "type": "item",
            "title": "Teen Wolf: The Movie (2023)",
            "link": [
            "https://hexupload.net/lb5qgwr4pkpt([COLORlime]FHD[/COLOR])"
        ],
            "thumbnail": "https://i.imgur.com/YVEfFGZ.jpg",
            "summary": "Action/Drama/Fantasy/Romance/Thriller",
            "imdb": "tt15486810"
        },
        {
            "type": "item",
            "title": "Imani (2023)",
            "link": [
            "https://racaty.io/kpwb0gofwxu7([COLORlime]FHD[/COLOR])"
        ],
            "thumbnail": "https://i.imgur.com/RAMOoPa.jpg",
            "summary": "Action/Thriller",
            "imdb": "tt21967864"
        },
        {
            "type": "item",
            "title": "Night Train (2023)",
            "link": [
            "https://hexupload.net/p8n7msyxxf0c([COLORlime]FHD[/COLOR])"
        ],
            "thumbnail": "https://i.imgur.com/TVIX4iG.jpg",
            "summary": "Action/Thriller",
            "imdb": "tt15727212"
        },
        {
            "type": "item",
            "title": "Candy Land (2022)",
            "link": [
            "https://racaty.io/q63mtzenf4sj([COLORlime]FHD[/COLOR])"
        ],
            "thumbnail": "https://i.imgur.com/0XSsT4u.jpg",
            "summary": "Horror/Thriller",
            "imdb": "tt13857556"
        },
        {
            "type": "item",
            "title": "Bezos (2023)",
            "link": [
            "https://hexupload.net/vhlxjj1gipow([COLORlime]FHD[/COLOR])"
        ],
            "thumbnail": "https://i.imgur.com/hy0Zrg8.jpg",
            "summary": "Biography/Drama/History",
            "imdb": "tt15559582"
        },
        {
            "type": "item",
            "title": "M3gan (2022)",
            "link": [
            "https://racaty.io/g6ksu5hvyhvw([COLORlime]FHD[/COLOR])"
        ],
            "thumbnail": "https://i.imgur.com/y5xkvwJ.jpg",
            "summary": "Horror/Sci-Fi/Thriller",
            "imdb": "tt8760708"
        },
        {
            "type": "item",
            "title": "Narvik (2022)",
            "link": [
            "https://hexupload.net/wmkmbpbtxgy2([COLORlime]FHD[/COLOR])"
        ],
            "thumbnail": "https://i.imgur.com/FTMkd37.jpg",
            "summary": "Drama/History/War",
            "imdb": "tt9737876"
        },
        {
            "type": "item",
            "title": "All Eyes (2022)",
            "link": [
            "https://hexupload.net/zm0b9r9iomo2([COLORlime]FHD[/COLOR])"
        ],
            "thumbnail": "https://i.imgur.com/Y69Ohg4.jpg",
            "summary": "Thriller",
            "imdb": "tt13101714"
        },
        {
            "type": "item",
            "title": "Bad Behind Bars: Jodi Arias (2023)",
            "link": [
            "https://doodstream.com/d/kd832coa5a81([COLORlime]FHD[/COLOR])"
        ],
            "thumbnail": "https://i.imgur.com/ChbCtj6.jpg",
            "summary": "Crime/Drama",
            "imdb": "tt23695384"
        },
        {
            "type": "item",
            "title": "Betrayed by My Bridesmaid (2022)",
            "link": [
            "https://doodstream.com/d/mjyric11ywku([COLORlime]FHD[/COLOR])"
        ],
            "thumbnail": "https://i.imgur.com/G4LBRmR.jpg",
            "summary": "Thriller",
            "imdb": "tt22814042"
        },
        {
            "type": "item",
            "title": "The Plot to Kill My Mother (2023)",
            "link": [
            "https://doodstream.com/d/rh8qyp9epog9([COLORlime]FHD[/COLOR])"
        ],
            "thumbnail": "https://i.imgur.com/edw2aIW.jpg",
            "summary": "Thriller",
            "imdb": "tt26215632"
        },
        {
            "type": "item",
            "title": "The Offering (2023)",
            "link": [
            "https://hexupload.net/2egfblrtsj48([COLORlime]FHD[/COLOR])"
        ],
            "thumbnail": "https://i.imgur.com/0tyZSJL.jpg",
            "summary": "Horror",
            "imdb": "tt13103732"
        },
        {
            "type": "item",
            "title": "Jung_E (2023)",
            "link": [
            "https://hexupload.net/qedtqcqb2twa([COLORlime]FHD[/COLOR])"
        ],
            "thumbnail": "https://i.imgur.com/64tCLXD.jpg",
            "summary": "Action/Adventure/Drama/Sci-Fi",
            "imdb": "tt22352848"
        },
        {
            "type": "item",
            "title": "Mega Lightning (2023)",
            "link": [
            "https://doodstream.com/d/c2212g9kj9dx([COLORlime]FHD[/COLOR])"
        ],
            "thumbnail": "https://i.imgur.com/u93kXkg.jpg",
            "summary": "Action/Horror",
            "imdb": "tt19119598"
        },
        {
            "type": "item",
            "title": "Transfusion (2023)",
            "link": [
            "https://hexupload.net/9r29s48hj4xv([COLORyellow]UHD[/COLOR])"
        ],
            "thumbnail": "https://i.imgur.com/w8XIcws.jpg",
            "summary": "Crime/Drama/Thriller",
            "imdb": "tt14873054"
        },
        {
            "type": "item",
            "title": "Black Warrant (2022)",
            "link": [
            "https://hexupload.net/ic52n2e1vpnn([COLORlime]FHD[/COLOR])"
        ],
            "thumbnail": "https://i.imgur.com/zcVNBO5.jpg",
            "summary": "Action/Thriller/",
            "imdb": "tt11696342"
        },
        {
            "type": "item",
            "title": "Detective Knight: Independence (2023)",
            "link": [
            "https://hexupload.net/sl6ynl8deg8x([COLORlime]FHD[/COLOR])"
        ],
            "thumbnail": "https://i.imgur.com/O7ds3bZ.jpg",
            "summary": "Action/Thriller/Crime",
            "imdb": "tt22394702"
        },
        {
            "type": "item",
            "title": "Sorry About the Demon (2022)",
            "link": [
            "https://doodstream.com/d/ek2blnsi2kgk([COLORlime]FHD[/COLOR])"
        ],
            "thumbnail": "https://i.imgur.com/KtZWZcm.jpg",
            "summary": "Comedy/Horror",
            "imdb": "tt15262634"
        },
        {
            "type": "item",
            "title": "The Price We Pay (2023)",
            "link": [
            "https://racaty.io/mjldffs9qydw([COLORlime]FHD[/COLOR])"
        ],
            "thumbnail": "https://i.imgur.com/F2NawKt.jpg",
            "summary": "Action/Horror/Thriller",
            "imdb": "tt15441472"
        },
        {
            "type": "item",
            "title": "Play Dead (2022)",
            "link": [
            "https://doodstream.com/d/xlisvdbwft26([COLORlime]FHD[/COLOR])"
        ],
            "thumbnail": "https://i.imgur.com/ZuIw20i.jpg",
            "summary": "Horror/Thriller",
            "imdb": "tt20198774"
        },
        {
            "type": "item",
            "title": "Seriously Red (2022)",
            "link": [
            "https://doodstream.com/d/ozhx9uyp5j1g([COLORlime]FHD[/COLOR])"
        ],
            "thumbnail": "https://i.imgur.com/LUloOkT.jpg",
            "summary": "Comedy/Drama/Music/Musical/Romance",
            "imdb": "tt4586828"
        },
        {
            "type": "item",
            "title": "House Party (2023)",
            "link": [
            "https://hexupload.net/5ngukt50150u([COLORlime]FHD[/COLOR])"
        ],
            "thumbnail": "https://i.imgur.com/lQDA6rx.jpg",
            "summary": "Comedy",
            "imdb": "tt8005118"
        },
        {
            "type": "item",
            "title": "There's Something Wrong with the Children (2023)",
            "link": [
            "https://doodstream.com/d/j2rzo4xq2pw3([COLORlime]FHD[/COLOR])"
        ],
            "thumbnail": "https://i.imgur.com/FfnV3z4.jpg",
            "summary": "Horror/Mystery",
            "imdb": "tt16127696"
        },
        {
            "type": "item",
            "title": "Snow Falls (2023)",
            "link": [
            "https://doodstream.com/d/iabbz79gv2fr([COLORlime]FHD[/COLOR])"
        ],
            "thumbnail": "https://i.imgur.com/Lrss0Sh.jpg",
            "summary": "Horror",
            "imdb": "tt11569658"
        },
        {
            "type": "item",
            "title": "Don't Look Deeper (2022)",
            "link": [
            "https://hexupload.net/71fm3zcizcew([COLORlime]FHD[/COLOR])"
        ],
            "thumbnail": "https://i.imgur.com/InVfBcA.jpg",
            "imdb": "tt22811298"
        },
        {
            "type": "item",
            "title": "Halloween Friends (2022) [COLORblue]Comedy[/COLOR]",
            "link": [
            "https://hexupload.net/yab74mt4vq80([COLORlime]FHD[/COLOR])"
        ],
            "thumbnail": "https://i.imgur.com/g8mOzZj.jpg",
            "imdb": "tt21847522"
        },
        {
            "type": "item",
            "title": "Battlebox (2023) [COLORblue]Drama/History/War[/COLOR]",
            "link": [
            "https://hexupload.net/zvz31yov3ojv([COLORlime]FHD[/COLOR])"
        ],
            "thumbnail": "https://i.imgur.com/T3dnqOa.jpg",
            "imdb": "tt14085258"
        },
        {
            "type": "item",
            "title": "The Falling World (2022) [COLORblue]Drama[/COLOR]",
            "link": [
            "https://hexupload.net/xbvcldq4vuiw([COLORlime]FHD[/COLOR])"
        ],
            "thumbnail": "https://i.imgur.com/OfFXK7a.jpg",
            "imdb": "tt13374994"
        },
        {
            "type": "item",
            "title": "Ghost Party (2022) [COLORblue]Mystery[/COLOR]",
            "link": [
            "https://hexupload.net/yuwir0jf3ozq([COLORlime]FHD[/COLOR])"
        ],
            "thumbnail": "https://i.imgur.com/OImUIQF.jpg",
            "imdb": "tt13846114"
        },
        {
            "type": "item",
            "title": "Bank of Dave (2023) [COLORblue]Bio/Comedy/Drama[/COLOR]",
            "link": [
            "https://hexupload.net/208ocuz9e0jd([COLORlime]FHD[/COLOR])"
        ],
            "thumbnail": "https://i.imgur.com/XDZahw3.jpg",
            "imdb": "tt14308636"
        },
        {
            "type": "item",
            "title": "Burned by Love (2023) [COLORblue]Mystery[/COLOR]",
            "link": [
            "https://doodstream.com/d/geg0hp8dcvha([COLORred]HD[/COLOR])"
        ],
            "thumbnail": "https://i.imgur.com/S3MXzcQ.jpg",
            "imdb": "tt26254288"
        },
         {
            "type": "item",
            "title": "Ricky Gervais: SuperNature (2022) [COLORgold]UHD[/COLOR]",
            "link": [
            "https://hexupload.net/9lso7vvpxsh6([COLORyellow]UHD[/COLOR])"
        ],
            "thumbnail": "https://i.imgur.com/NJUOcq9.jpg"
        },
        {
            "type": "item",
            "title": "Ricky Gervais: SuperNature (2022) [COLORblue]Action/Comedy[/COLOR]",
            "link": [
            "https://doodstream.com/d/o7hra3oc8u79([COLORlime]FHD[/COLOR])"
        ],
            "thumbnail": "https://i.imgur.com/NJUOcq9.jpg"
        },
        {
            "type": "item",
            "title": "Disconnect: The Wedding Planner (2023) [COLORblue]Comedy/Romance[/COLOR]",
            "link": [
            "https://hexupload.net/orzxptq9ot55([COLORlime]FHD[/COLOR])"
        ],
            "thumbnail": "https://i.imgur.com/kqhvgxj.jpg",
            "imdb": "tt24640474"
        },
        {
            "type": "item",
            "title": "Dog Gone (2023) [COLORblue]Bio/Drama/Family[/COLOR]",
            "link": [
            "https://hexupload.net/rw9ol394eir2([COLORlime]FHD[/COLOR])"
        ],
            "thumbnail": "https://i.imgur.com/o8aYKS9.jpg",
            "imdb": "tt15334430"
        },
        {
            "type": "item",
            "title": "Sick (2022) [COLORgold]UHD[/COLOR]",
            "link": [
            "https://hexupload.net/1lr26uzd3qu8([COLORyellow]UHD[/COLOR])"
        ],
            "thumbnail": "https://i.imgur.com/ubHoXM3.jpg",
            "imdb": "tt14642626"
        },
        {
            "type": "item",
            "title": "Sick (2022) [COLORblue]Horror/Thriller[/COLOR]",
            "link": [
            "https://hexupload.net/1lr26uzd3qu8([COLORyellow]UHD[/COLOR])"
        ],
            "thumbnail": "https://i.imgur.com/ubHoXM3.jpg",
            "imdb": "tt14642626"
        },
        {
            "type": "item",
            "title": "The Old Way (2023) [COLORblue]Action/Western[/COLOR]",
            "link": [
            "https://hexupload.net/3oq9y28pnubj([COLORlime]FHD[/COLOR])"
        ],
            "thumbnail": "https://i.imgur.com/gYyicx2.jpg",
            "imdb": "tt8593824"
        },
        {
            "type": "item",
            "title": "The Drop (2022) [COLORblue]Comedy[/COLOR]",
            "link": [
            "https://hexupload.net/fnnpupcuxs5e([COLORlime]FHD[/COLOR])"
        ],
            "thumbnail": "https://i.imgur.com/SWF6SZ2.jpg",
            "imdb": "tt19758112"
        },
        {
            "type": "item",
            "title": "The Time Capsule (2022) [COLORblue]Drama/Romance/Sci-Fi[/COLOR]",
            "link": [
            "https://doodstream.com/d/k6dhrfo47ui7([COLORyellow]UHD[/COLOR])"
        ],
            "thumbnail": "https://i.imgur.com/581ebL8.jpg",
            "imdb": "tt10418680"
        },
        {
            "type": "item",
            "title": "The Most Dangerous Game (2022) [COLORblue]Thriller[/COLOR]",
            "link": [
            "https://doodstream.com/d/us6a1by3evh8([COLORlime]FHD[/COLOR])"
        ],
            "thumbnail": "https://i.imgur.com/HdqcFpD.jpg",
            "imdb": "tt15822738"
        },
        {
            "type": "item",
            "title": "Bed Rest (2022) [COLORblue]Drama/Horror/Mystery[/COLOR]",
            "link": [
            "https://doodstream.com/d/ohg14yx3oj0z([COLORyellow]UHD[/COLOR])"
        ],
            "thumbnail": "https://i.imgur.com/RBTQ41I.jpg",
            "imdb": "tt4896168"
        },
         {
            "type": "item",
            "title": "Devotion (2022) [COLORgold]UHD[/COLOR]",
            "link": [
            "https://hexupload.net/zfok0cgv6dyl([COLORyellow]UHD[/COLOR])"
        ],
            "thumbnail": "https://i.imgur.com/ZvlWHYK.jpg",
            "imdb": "tt7693316"
        },
        {
            "type": "item",
            "title": "Devotion (2022) [COLORblue]Action/Drama/War[/COLOR]",
            "link": [
            "https://hexupload.net/8bky9z2cf5jo([COLORlime]FHD[/COLOR])"
        ],
            "thumbnail": "https://i.imgur.com/ZvlWHYK.jpg",
            "imdb": "tt7693316"
        },
        {
            "type": "item",
            "title": "Funny Pages (2022) [COLORblue]Comedy[COLORred] (Rated-R)[/COLOR]",
            "link": [
            "https://doodstream.com/d/daoybjo5php4([COLORyellow]UHD[/COLOR])"
        ],
            "thumbnail": "https://i.imgur.com/7R1RQcS.jpg",
            "imdb": "tt8174412"
        },
        {
            "type": "item",
            "title": "Caliovas (2022) [COLORblue]Fantasy/Mystery/Sci-Fi[/COLOR]",
            "link": [
            "https://doodstream.com/d/6ecqxk0xempn([COLORyellow]UHD[/COLOR])"
        ],
            "thumbnail": "https://i.imgur.com/zrEF7uq.jpg",
            "imdb": "tt15501758"
        },
        {
            "type": "item",
            "title": "The Pale Blue Eye (2022) [COLORblue]Crime/Horror/Mystery/Thriller[/COLOR]",
            "link": [
            "https://hexupload.net/8enmw8jc1x0f([COLORlime]FHD[/COLOR])"
        ],
            "thumbnail": "https://i.imgur.com/HJ0IiDe.jpg",
            "imdb": "tt14138650"
        },
        {
            "type": "item",
            "title": "Puss in Boots: The Last Wish (2022) [COLORgold]UHD[/COLOR]",
            "link": [
            "https://hexupload.net/gbjpn4jfxfgh([COLORyellow]UHD[/COLOR])"
        ],
            "thumbnail": "https://i.imgur.com/ZcB2zOw.jpg",
            "imdb": "tt3915174"
        },
        {
            "type": "item",
            "title": "Puss in Boots: The Last Wish (2022) [COLORblue]Ani/Adv/Com/Fam/Fan/Mys/Rom[/COLOR]",
            "link": [
            "https://hexupload.net/a6hb3gbunquy([COLORlime]FHD[/COLOR])"
        ],
            "thumbnail": "https://i.imgur.com/ZcB2zOw.jpg",
            "imdb": "tt3915174"
        },
        {
            "type": "item",
            "title": "Matriarch (2022) [COLORblue]Horror[/COLOR]",
            "link": [
            "https://doodstream.com/d/05pihra4xipn([COLORyellow]UHD[/COLOR])"
        ],
            "thumbnail": "https://i.imgur.com/j17yIYn.jpg",
            "imdb": "tt17202326"
        },
        {
            "type": "item",
            "title": "Sinphony (2022) [COLORblue]Horror[/COLOR]",
            "link": [
            "https://doodstream.com/d/xdvwdhu8cxuy([COLORyellow]UHD[/COLOR])"
        ],
            "thumbnail": "https://i.imgur.com/XhNVh4a.jpg",
            "imdb": "tt14202334"
        },
         {
            "type": "item",
            "title": "The Menu (2022) [COLORgold]UHD[/COLOR]",
            "link": [
            "https://racaty.io/zlo6j7lav34t([COLORyellow]UHD[/COLOR])"
        ],
            "thumbnail": "https://i.imgur.com/4gVOcED.jpg",
            "imdb": "tt9764362"
        {
            "type": "item",
            "title": "The Menu (2022) [COLORblue]Horror (89%-RT)[/COLOR]",
            "link": [
            "https://racaty.io/626u0takx2io([COLORlime]FHD[/COLOR])"
        ],
            "thumbnail": "https://i.imgur.com/4gVOcED.jpg",
            "imdb": "tt9764362"
        },
        {
            "type": "item",
            "title": "Glass Onion: A Knives Out Mystery (2022) [COLORgold]UHD[/COLOR]",
            "link": [
            "https://hexupload.net/t8g2p54dfffn([COLORyellow]UHD[/COLOR])"
        ],
            "thumbnail": "https://i.imgur.com/LjHCVzF.jpg",
            "imdb": "tt11564570"
        },
        {
            "type": "item",
            "title": "Glass Onion: A Knives Out Mystery (2022) [COLORblue]Crime/Drama/Thriller (93%-RT)[/COLOR]",
            "link": [
            "https://racaty.io/o3owtk2kmbor([COLORlime]FHD[/COLOR])"
        ],
            "thumbnail": "https://i.imgur.com/LjHCVzF.jpg",
            "imdb": "tt11564570"
        },
         {
            "type": "item",
            "title": "Catfish Killer (2022) [COLORblue]Thriller[/COLOR]",
            "link": [
            "https://doodstream.com/d/g7v9us2ujzo0([COLORred]HD[/COLOR])"
        ],
            "thumbnail": "https://i.imgur.com/HgX0KrL.jpg",
            "imdb": "tt18395072"
        },
        {
            "type": "item",
            "title": "The Last Heist (2022) [COLORblue]Crime[/COLOR]",
            "link": [
            "https://racaty.io/ud75748255ol([COLORlime]FHD[/COLOR])"
        ],
            "thumbnail": "https://i.imgur.com/4ldgOzg.jpg",
            "imdb": "tt21045742"
        },
        {
            "type": "item",
            "title": "Don't F*ck in the Woods 2 (2022) [COLORblue]Horror[/COLOR]",
            "link": [
            "https://racaty.io/k3lkpq80jtup([COLORlime]FHD[/COLOR])"
        ],
            "thumbnail": "https://i.imgur.com/5BlQaRm.jpg",
            "imdb": "tt7560830"
        },
         {
            "type": "item",
            "title": "White Noise (2022) [COLORblue]Comedy/Drama/Horror/Mystery[/COLOR]",
            "link": [
            "https://racaty.io/0f2nyfe4kbpw([COLORlime]FHD[/COLOR])"
        ],
            "thumbnail": "https://i.imgur.com/lUjfSIj.jpg",
            "imdb": "tt6160448"
        },
        {
            "type": "item",
            "title": "Lamborghini The Man Behind The Legend (2022) [COLORblue]Bio/Drama/Sport[/COLOR]",
            "link": [
            "https://racaty.io/f0n4e4936h1f([COLORlime]FHD[/COLOR])"
        ],
            "thumbnail": "https://i.imgur.com/Aerx7KY.jpg",
            "imdb": "tt5533370"
        },
        {
            "type": "item",
            "title": "Lullaby (2022) [COLORblue]Horror[/COLOR]",
            "link": [
            "https://streamtape.com/v/3pvvoGOb82HdBJa/([COLORlime]FHD[/COLOR])"
        ],
            "thumbnail": "https://i.imgur.com/XjXxM3R.jpg",
            "imdb": "tt11891246"
        },
        {
            "type": "item",
            "title": "The Irish Connection (2022) [COLORblue]Action/Adventure[/COLOR]",
            "link": [
            "https://doodstream.com/d/fbv6t3ogmtq4([COLORlime]FHD[/COLOR])"
        ],
            "thumbnail": "https://i.imgur.com/nOHrzjc.jpg",
            "imdb": "tt10164206"
        },
        {
            "type": "item",
            "title": "The Boy, the Mole, the Fox and the Horse (2022) [COLORblue]Animation/Family (81%)[/COLOR]",
            "link": [
            "https://racaty.io/k6m16lmig1ql([COLORlime]FHD[/COLOR])"
        ],
            "thumbnail": "https://i.imgur.com/OI22nFE.jpg",
            "imdb": "tt22667880"
        },
        {
            "type": "item",
            "title": "Roald Dahl's Matilda the Musical (2022) [COLORblue]Comedy/Drama/Family/Fantasy/Musical (90%-RT)[/COLOR]",
            "link": [
            "https://racaty.io/tyvzsp2re4u8([COLORlime]FHD[/COLOR])"
        ],
            "thumbnail": "https://i.imgur.com/bHjjzF4.jpg",
            "imdb": "tt3447590"
        },
        {
            "type": "item",
            "title": "As a Prelude to Fear (2022) [COLORblue]Horror/Thriller[/COLOR]",
            "link": [
            "https://doodstream.com/d/se7n6m7p74pj([COLORlime]FHD[/COLOR])"
        ],
            "thumbnail": "https://i.imgur.com/YZlyqJP.jpg",
            "imdb": "tt3804376"
        },
        {
            "type": "item",
            "title": "Spoiler Alert (2022) [COLORblue]Comedy/Drama (83%-RT)[/COLOR]",
            "link": [
            "https://racaty.io/foszg21koq5c([COLORlime]FHD[/COLOR])"
        ],
            "thumbnail": "https://i.imgur.com/pRacYrU.jpg",
            "imdb": "tt7775720"
        },
        {
            "type": "item",
            "title": "Glass Onion: A Knives Out Mystery (2022) [COLORblue]Crime/Drama/Thriller (93%-RT)[/COLOR]",
            "link": [
            "https://racaty.io/o3owtk2kmbor([COLORlime]FHD[/COLOR])"
        ],
            "thumbnail": "https://i.imgur.com/LjHCVzF.jpg",
            "imdb": "tt11564570"
        },
        {
            "type": "item",
            "title": "Strange World (2022) [COLORblue]Animation/Action/Adventure/Comedy/Family/Fantasy/Sci-Fi[/COLOR]",
            "link": [
            "https://racaty.io/gekzgfcalf90([COLORlime]FHD[/COLOR])"
        ],
            "thumbnail": "https://i.imgur.com/4r95yqm.jpg",
            "imdb": "tt10298840"
        },
        {
            "type": "item",
            "title": "Mad Heidi (2022) [COLORblue]Action/Adventure/Comed/Fantasy/Horror[/COLOR]",
            "link": [
            "https://racaty.io/t07b5oyjqosg([COLORlime]FHD[/COLOR])"
        ],
            "thumbnail": "https://i.imgur.com/HBSbiI5.jpg",
            "imdb": "tt2943178"
        },
        {
            "type": "item",
            "title": "The Leech (2022) [COLORblue]Comedy/Horror[/COLOR]",
            "link": [
            "https://racaty.io/ubemjjsxzuwj([COLORlime]FHD[/COLOR])"
        ],
            "thumbnail": "https://i.imgur.com/m3JlA4b.jpg",
            "imdb": "tt13998454"
        },
        {
            "type": "item",
            "title": "Scare Package II: Rad Chad's Revenge (2022) [COLORblue]Comedy/Horror[/COLOR]",
            "link": [
            "https://racaty.io/t77bjjxd624y([COLORlime]FHD[/COLOR])"
        ],
            "thumbnail": "https://i.imgur.com/Qwrohfb.jpg",
            "imdb": "tt16426066"
        },
        {
            "type": "item",
            "title": "Suitcase Killer: The Melanie McGuire Story (2022) [COLORblue]Drama/Mystery[/COLOR]",
            "link": [
            "https://streamtape.com/v/oLdBrDX7M2IbOz/([COLORlime]FHD[/COLOR])"
        ],
            "thumbnail": "https://i.imgur.com/UszUdtu.jpg",
            "imdb": "tt19813094"
        },
        {
            "type": "item",
            "title": "Wog Boys Forever (2022) [COLORblue]Comedy[/COLOR]",
            "link": [
            "https://racaty.io/dcypsbrg4xhb([COLORlime]FHD[/COLOR])"
        ],
            "thumbnail": "https://i.imgur.com/KC4TixR.jpg",
            "imdb": "tt14909354"
        },
        {
            "type": "item",
            "title": "With/In (2021) [COLORblue]Drama[/COLOR]",
            "link": [
            "https://racaty.io/x4ovbij40tm7([COLORlime]FHD[/COLOR])"
        ],
            "thumbnail": "https://i.imgur.com/UATdtht.jpg",
            "imdb": "tt2193173"
        },
        {
            "type": "item",
            "title": "Mad God (2021) [COLORblue]Animation/Fantasy/Horror/Sci-Fi[/COLOR]",
            "link": [
            "https://racaty.io/vnlqpnabdb7d([COLORlime]FHD[/COLOR])"
        ],
            "thumbnail": "https://i.imgur.com/olNqMyd.jpg",
            "imdb": "tt15090124"
        },
        {
            "type": "item",
            "title": "Monsters in the Closet (2022) [COLORblue]Comedy/Thriller[/COLOR]",
            "link": [
            "https://racaty.io/3jrd40xs08v5([COLORlime]FHD[/COLOR])"
        ],
            "thumbnail": "https://i.imgur.com/BXNno6O.jpg",
            "imdb": "tt15295190"
        },
        {
            "type": "item",
            "title": "The Last Slay Ride (2022) [COLORblue]Comedy[/COLOR]",
            "link": [
            "https://racaty.io/trieq1n4o6mi([COLORlime]FHD[/COLOR])"
        ],
            "thumbnail": "https://i.imgur.com/I7cZzoB.jpg",
            "imdb": "tt15139470"
        },
        {
            "type": "item",
            "title": "The African Desperate (2022) [COLORblue]Comedy/Drama[/COLOR]",
            "link": [
            "https://racaty.io/daoe37e55g5r([COLORlime]FHD[/COLOR])"
        ],
            "thumbnail": "https://i.imgur.com/6L8f0fc.jpg",
            "imdb": "tt17048276"
        },
        {
            "type": "item",
            "title": "When Are You Moving Out? (2022) [COLORblue]Comedy[/COLOR]",
            "link": [
            "https://racaty.io/5cqqwswthyck([COLORlime]FHD[/COLOR])"
        ],
            "thumbnail": "https://i.imgur.com/JyZSDHJ.jpg",
            "imdb": "tt18927992"
        },
        {
            "type": "item",
            "title": "Heart of the Gun (2022) [COLORblue]Western[/COLOR]",
            "link": [
            "https://racaty.io/17k3y1ji6cre([COLORlime]FHD[/COLOR])"
        ],
            "thumbnail": "https://i.imgur.com/lCnt7KE.jpg",
            "imdb": "tt6866062"
        },
        {
            "type": "item",
            "title": "The Pebble and the Boy (2021) [COLORblue]Drama[/COLOR]",
            "link": "https://racaty.io/1fg0s1c46op8",
            "thumbnail": "https://i.imgur.com/tH0V8T9.jpg",
            "imdb": "tt10773626"
        },
        {
            "type": "item",
            "title": "Aftersun (2022) [COLORblue]Drama[/COLOR]",
            "link": [
            "https://racaty.io/zojfoa3vnthz([COLORlime]FHD[/COLOR])"
        ],
            "thumbnail": "https://i.imgur.com/r8T25RN.jpg",
            "imdb": "tt19770238"
        },
        {
            "type": "item",
            "title": "Violent Night (2022) [COLORblue]Action/Comedy/Crime/Thriller[/COLOR]",
            "link": [
            "https://racaty.io/saj5y6ydr8yf([COLORlime]FHD[/COLOR])"
        ],
            "thumbnail": "https://i.imgur.com/2FfEt9c.jpg",
            "imdb": "tt12003946"
        },
        {
            "type": "item",
            "title": "Ashgrove (2022) [COLORblue]Drama[/COLOR]",
            "link": [
            "https://racaty.io/879lxnjrwrnx([COLORlime]FHD[/COLOR])"
        ],
            "thumbnail": "https://i.imgur.com/dgTypjM.jpg",
            "imdb": "tt17495872"
        },
        {
            "type": "item",
            "title": "Beauty and the Beast: A 30th Celebration (2022) [COLORblue]Animation/Adventure/Family/Musical/Romance[/COLOR]",
            "link": [
            "https://streamtape.com/v/2r4e2PrZ2ZFRBP/([COLORlime]FHD[/COLOR])"
        ],
            "thumbnail": "https://i.imgur.com/jYl93Jr.jpg",
            "imdb": "tt21220842"
        },
        {
            "type": "item",
            "title": "Plus One at an Amish Wedding (2022) [COLORblue]Comedy/Romance[/COLOR]",
            "link": [
            "https://streamtape.com/v/VOmyLYdAbruKpoM/([COLORlime]FHD[/COLOR])"
        ],
            "thumbnail": "https://i.imgur.com/afPWOdq.jpg",
            "imdb": "tt17178096"
        },
        {
            "type": "item",
            "title": "High Heat (2022) [COLORblue]Action/Comedy[/COLOR]",
            "link": [
            "https://racaty.io/s2yrt5uhkauy([COLORlime]FHD[/COLOR])"
        ],
            "thumbnail": "https://i.imgur.com/dMNKRFA.jpg",
            "imdb": "tt15721088"
        },
        {
            "type": "item",
            "title": "Plebs: Soldiers of Rome (2022)* [COLORblue]Adventure/Comedy/War[/COLOR]",
            "link": [
            "https://racaty.io/tusdsd90vn3j([COLORlime]FHD[/COLOR])"
            ],
            "thumbnail": "https://i.imgur.com/o0ODsia.jpg",
            "imdb": "tt22817698"
        },
        {
            "type": "item",
            "title": "The Hanging Sun (2022) [COLORblue]Crime/Drama/Mystery/Romance[/COLOR]",
            "link": [
            "https://racaty.io/w29b1l6rn1aa([COLORlime]FHD[/COLOR])"
        ],
            "thumbnail": "https://i.imgur.com/tBMdmyJ.jpg",
            "imdb": "tt6986990"
        },
        {
            "type": "item",
            "title": "The Amazing Maurice (2022) [COLORblue]Animation/Adventure/Comedy/Family[/COLOR]",
            "link": [
            "https://racaty.io/a0trxe8felrf([COLORlime]FHD[/COLOR])"
        ],
            "thumbnail": "https://i.imgur.com/5kVXcYu.jpg",
            "imdb": "tt10473036"
        },
        {
            "type": "item",
            "title": "Dead for a Dollar (2022) [COLORblue]Action/Thriller/Western[/COLOR]",
            "link": [
            "https://racaty.io/5e79pgljkcw5([COLORlime]FHD[/COLOR])"
            ],
            "thumbnail": "https://i.imgur.com/Xda7odO.jpg",
            "imdb": "tt14895206"
        },
        {
            "type": "item",
            "title": "Renegades (2022) [COLORblue]Action/Crime/Thriller[/COLOR]",
            "link": [
            "https://racaty.io/fgm204ifqqcw([COLORlime]FHD[/COLOR])"
            ],
            "thumbnail": "https://i.imgur.com/YURFaD8.jpg",
            "imdb": "tt11696276"
        },
        {
            "type": "item",
            "title": "The Honeymoon (2022) [COLORblue]Comedy[/COLOR]",
            "link": [
            "https://racaty.io/gw3fjvd4nnlh([COLORlime]FHD[/COLOR])"
            ],
            "thumbnail": "https://i.imgur.com/3QJzuK5.jpg",
            "imdb": "tt14781026"
        },
        {
            "type": "item",
            "title": "One Way (2022) [COLORblue]Action/Thriller[/COLOR]",
            "link": [
            "https://racaty.io/gk9gagsfommn([COLORlime]FHD[/COLOR])"
            ],
            "thumbnail": "https://i.imgur.com/CbvNNeV.jpg",
            "imdb": "tt13075730"
        },
  
        {
            "type": "dir",
            "title": "[COLORyellow]>>>> Next Page >>>>>[/COLOR]",
            "link": "https://bitbucket.org/Mad-Eric/textfiles/raw/master/nr2.json",
            "thumbnail": "https://i.imgur.com/r6nMlcQ.png"
        }
       
    ]
}
