  {
    "items": [
  
       {   "type": "item",
            "title": "The Karate Kid (1984)",
            "link": "search", 
            "year": "1984",
            "content": "movie",
            "thumbnail": "https://www.themoviedb.org/t/p/w600_and_h900_bestv2/jHaigBR6Zg7paCeRpTryjJHle1u.jpg",
            "imdb_id": "" 
        },
		    {   "type": "item",
            "title": "The Karate Kid Part II (1986)",
            "link": "search", 
            "year": "1986",
            "content": "movie",
            "thumbnail": "https://www.themoviedb.org/t/p/w600_and_h900_bestv2/k0OwgRR6PNu7h3SiqpCbRdZWNaG.jpg",
            "imdb_id": "" 
        },
		    {   "type": "item",
            "title": "The Karate Kid Part III (1989)",
            "link": "search", 
            "year": "1989",
            "content": "movie",
            "thumbnail": "https://www.themoviedb.org/t/p/w600_and_h900_bestv2/5qVjJGzPokkK7OYA65hYb1fGsJQ.jpg",
            "imdb_id": "" 
        }
        
   ]
   
  }
